{
  "question_id": "a4996e51",
  "question_type": "multi-session",
  "question_date": "2023/05/30 (Tue) 15:17",
  "num_sessions": 48,
  "num_turns": 512,
  "answer_session_ids": [
    "answer_feb5f98a_1",
    "answer_feb5f98a_2"
  ],
  "session_ids": [
    "bb236214",
    "c1dac02f",
    "sharegpt_58CEDM8_0",
    "f379d356_3",
    "ultrachat_162074",
    "sharegpt_OKduwwf_0",
    "4cc9270f",
    "600077b0_1",
    "ultrachat_441327",
    "sharegpt_BvuMJIh_81",
    "sharegpt_LYRqOF7_9",
    "8d30ec5b",
    "ef0341d4_2",
    "sharegpt_KjF70Iy_0",
    "sharegpt_E0YL5SX_291",
    "add009ef_2",
    "ultrachat_64410",
    "sharegpt_tvcY0lQ_0",
    "ultrachat_286075",
    "answer_feb5f98a_1",
    "sharegpt_fw0xeSU_0",
    "e9fba4f8",
    "d1a61aa1_3",
    "2ca99347_2",
    "ultrachat_265159",
    "sharegpt_vHIFuaD_0",
    "eea3e4be_2",
    "4f2d6be4_2",
    "28a64f28_2",
    "85a1c17b_5",
    "ultrachat_386206",
    "ultrachat_258111",
    "5dbb6a80_2",
    "8f3831ac",
    "252715f8_3",
    "sharegpt_oWUj0Se_0",
    "ultrachat_353878",
    "726e9a1f_3",
    "11660eb5_1",
    "ultrachat_506025",
    "ultrachat_295714",
    "b1d9eb66_3",
    "aa8ebe6c",
    "answer_feb5f98a_2",
    "082b7e52_2",
    "ultrachat_516576",
    "16bd5ea5_1",
    "sharegpt_xtXzOxh_71"
  ],
  "dates": [
    "2023/05/20 (Sat) 01:51",
    "2023/05/20 (Sat) 02:51",
    "2023/05/20 (Sat) 10:34",
    "2023/05/20 (Sat) 14:07",
    "2023/05/20 (Sat) 19:34",
    "2023/05/21 (Sun) 02:34",
    "2023/05/21 (Sun) 16:27",
    "2023/05/21 (Sun) 18:12",
    "2023/05/21 (Sun) 19:51",
    "2023/05/21 (Sun) 22:50",
    "2023/05/22 (Mon) 00:59",
    "2023/05/22 (Mon) 03:44",
    "2023/05/22 (Mon) 06:23",
    "2023/05/22 (Mon) 06:58",
    "2023/05/22 (Mon) 14:55",
    "2023/05/23 (Tue) 01:06",
    "2023/05/23 (Tue) 09:12",
    "2023/05/23 (Tue) 13:08",
    "2023/05/23 (Tue) 15:29",
    "2023/05/24 (Wed) 07:36",
    "2023/05/24 (Wed) 15:05",
    "2023/05/25 (Thu) 03:21",
    "2023/05/25 (Thu) 09:20",
    "2023/05/25 (Thu) 14:08",
    "2023/05/25 (Thu) 14:36",
    "2023/05/25 (Thu) 21:57",
    "2023/05/26 (Fri) 00:15",
    "2023/05/26 (Fri) 02:19",
    "2023/05/26 (Fri) 04:03",
    "2023/05/26 (Fri) 12:43",
    "2023/05/26 (Fri) 14:13",
    "2023/05/26 (Fri) 14:15",
    "2023/05/27 (Sat) 01:39",
    "2023/05/27 (Sat) 03:17",
    "2023/05/27 (Sat) 17:20",
    "2023/05/27 (Sat) 21:20",
    "2023/05/27 (Sat) 23:00",
    "2023/05/28 (Sun) 01:37",
    "2023/05/28 (Sun) 15:10",
    "2023/05/28 (Sun) 17:07",
    "2023/05/28 (Sun) 21:53",
    "2023/05/29 (Mon) 00:33",
    "2023/05/29 (Mon) 01:09",
    "2023/05/29 (Mon) 02:54",
    "2023/05/29 (Mon) 07:59",
    "2023/05/29 (Mon) 14:40",
    "2023/05/29 (Mon) 23:24",
    "2023/05/30 (Tue) 01:20"
  ]
}