{
  "question_id": "21436231",
  "question_type": "single-session-user",
  "question_date": "2023/05/30 (Tue) 19:25",
  "num_sessions": 50,
  "num_turns": 512,
  "answer_session_ids": [
    "answer_1e6d4567"
  ],
  "session_ids": [
    "ultrachat_219234",
    "ultrachat_175807",
    "7a7a4bf0_4",
    "sharegpt_pMczn7z_0",
    "sharegpt_G8j6c8J_38",
    "ultrachat_281779",
    "answer_1e6d4567",
    "1b2b30d3",
    "ultrachat_159732",
    "e8b2d65e",
    "sharegpt_jyM2Qbm_0",
    "sharegpt_FsFEDQS_0",
    "2fd8bf73_1",
    "4bebc783_2",
    "sharegpt_uELkJdb_24",
    "ultrachat_155792",
    "3197d998_6",
    "a0f8468c_3",
    "ultrachat_148297",
    "ultrachat_388075",
    "sharegpt_omPL4EE_0",
    "c7c4cf1e_1",
    "6bd0b406_1",
    "a3058382_4",
    "f086cb61_3",
    "ultrachat_236469",
    "ultrachat_250763",
    "sharegpt_wrwD6bG_0",
    "sharegpt_NxG2nGm_298",
    "3fa35683_6",
    "sharegpt_I2cfkPp_63",
    "086777a8",
    "sharegpt_6byuqlt_0",
    "sharegpt_DGiqvVv_169",
    "ultrachat_115100",
    "sharegpt_jHGL67f_0",
    "sharegpt_EMlLNqy_15",
    "dc378711_1",
    "sharegpt_CjoQMV6_0",
    "ultrachat_249381",
    "b307196d",
    "ultrachat_23643",
    "sharegpt_3lWzv4B_0",
    "ultrachat_37989",
    "0d0a89dc_1",
    "a3118ef0_1",
    "9b820206",
    "d0785ee9_1",
    "sharegpt_I9Aziqq_1",
    "ultrachat_172276"
  ],
  "dates": [
    "2023/05/20 (Sat) 06:09",
    "2023/05/20 (Sat) 14:38",
    "2023/05/20 (Sat) 17:36",
    "2023/05/20 (Sat) 22:21",
    "2023/05/21 (Sun) 02:45",
    "2023/05/21 (Sun) 05:33",
    "2023/05/21 (Sun) 06:28",
    "2023/05/21 (Sun) 07:06",
    "2023/05/21 (Sun) 09:11",
    "2023/05/21 (Sun) 11:16",
    "2023/05/21 (Sun) 21:43",
    "2023/05/22 (Mon) 03:07",
    "2023/05/22 (Mon) 07:12",
    "2023/05/22 (Mon) 11:59",
    "2023/05/22 (Mon) 21:37",
    "2023/05/22 (Mon) 23:43",
    "2023/05/23 (Tue) 05:54",
    "2023/05/23 (Tue) 09:39",
    "2023/05/23 (Tue) 13:52",
    "2023/05/23 (Tue) 17:29",
    "2023/05/23 (Tue) 22:05",
    "2023/05/24 (Wed) 08:49",
    "2023/05/24 (Wed) 09:17",
    "2023/05/24 (Wed) 09:35",
    "2023/05/24 (Wed) 10:38",
    "2023/05/24 (Wed) 16:41",
    "2023/05/24 (Wed) 17:44",
    "2023/05/24 (Wed) 18:50",
    "2023/05/25 (Thu) 01:15",
    "2023/05/25 (Thu) 10:32",
    "2023/05/25 (Thu) 10:38",
    "2023/05/25 (Thu) 17:28",
    "2023/05/25 (Thu) 22:06",
    "2023/05/26 (Fri) 06:44",
    "2023/05/26 (Fri) 10:08",
    "2023/05/26 (Fri) 12:25",
    "2023/05/27 (Sat) 08:42",
    "2023/05/27 (Sat) 11:31",
    "2023/05/27 (Sat) 12:09",
    "2023/05/27 (Sat) 20:05",
    "2023/05/28 (Sun) 01:11",
    "2023/05/28 (Sun) 04:16",
    "2023/05/28 (Sun) 06:56",
    "2023/05/28 (Sun) 12:44",
    "2023/05/29 (Mon) 10:31",
    "2023/05/30 (Tue) 06:51",
    "2023/05/30 (Tue) 07:39",
    "2023/05/30 (Tue) 08:11",
    "2023/05/30 (Tue) 12:48",
    "2023/05/30 (Tue) 16:53"
  ]
}