{
  "question_id": "b320f3f8",
  "question_type": "single-session-user",
  "question_date": "2023/05/30 (Tue) 17:49",
  "num_sessions": 46,
  "num_turns": 463,
  "answer_session_ids": [
    "answer_5cc9b056"
  ],
  "session_ids": [
    "sharegpt_S8gExpS_35",
    "40628271_1",
    "sharegpt_ZB4vsDI_5",
    "sharegpt_4FCMpJR_0",
    "bee1aec6_3",
    "bff03174",
    "f50d2c98",
    "f7a94ac9_3",
    "ultrachat_151745",
    "ultrachat_19047",
    "ultrachat_136419",
    "sharegpt_7QD86cC_20",
    "1b71c896_2",
    "66ffbb8b_1",
    "ultrachat_562554",
    "sharegpt_bMeRfJz_0",
    "sharegpt_F5ZBqrY_53",
    "0ed551ec",
    "ultrachat_490693",
    "ultrachat_174996",
    "8f35cebe_2",
    "ultrachat_577414",
    "ultrachat_246708",
    "sharegpt_jrexRUl_43",
    "sharegpt_3w5VLHY_0",
    "sharegpt_o0MporM_0",
    "943fdca0",
    "5e4bb245_2",
    "240d7361_1",
    "d3a3f421_2",
    "sharegpt_VknhO3F_0",
    "8bb8bc0d",
    "85272e7e",
    "514a7856_2",
    "abecc1b6",
    "b89f68c4_4",
    "f2797fac",
    "sharegpt_auHASKv_0",
    "e28f75f4",
    "answer_5cc9b056",
    "sharegpt_IHPDBYP_0",
    "sharegpt_I6IzvEF_60",
    "sharegpt_mvtmr4e_19",
    "ultrachat_5758",
    "aae4411b_2",
    "ultrachat_29288"
  ],
  "dates": [
    "2023/05/20 (Sat) 01:24",
    "2023/05/20 (Sat) 08:53",
    "2023/05/20 (Sat) 08:53",
    "2023/05/20 (Sat) 19:44",
    "2023/05/21 (Sun) 06:37",
    "2023/05/21 (Sun) 20:53",
    "2023/05/22 (Mon) 02:44",
    "2023/05/22 (Mon) 02:46",
    "2023/05/22 (Mon) 04:38",
    "2023/05/22 (Mon) 23:06",
    "2023/05/23 (Tue) 10:09",
    "2023/05/23 (Tue) 17:02",
    "2023/05/23 (Tue) 18:32",
    "2023/05/23 (Tue) 20:06",
    "2023/05/24 (Wed) 01:43",
    "2023/05/24 (Wed) 07:06",
    "2023/05/24 (Wed) 08:51",
    "2023/05/24 (Wed) 14:44",
    "2023/05/24 (Wed) 16:40",
    "2023/05/24 (Wed) 19:30",
    "2023/05/24 (Wed) 21:40",
    "2023/05/24 (Wed) 22:44",
    "2023/05/25 (Thu) 01:18",
    "2023/05/25 (Thu) 07:43",
    "2023/05/25 (Thu) 13:44",
    "2023/05/25 (Thu) 20:05",
    "2023/05/26 (Fri) 12:22",
    "2023/05/26 (Fri) 14:32",
    "2023/05/26 (Fri) 15:18",
    "2023/05/26 (Fri) 15:36",
    "2023/05/26 (Fri) 21:37",
    "2023/05/27 (Sat) 08:39",
    "2023/05/27 (Sat) 17:07",
    "2023/05/28 (Sun) 08:17",
    "2023/05/28 (Sun) 08:53",
    "2023/05/28 (Sun) 21:28",
    "2023/05/29 (Mon) 04:49",
    "2023/05/29 (Mon) 08:39",
    "2023/05/29 (Mon) 11:32",
    "2023/05/29 (Mon) 13:48",
    "2023/05/29 (Mon) 15:24",
    "2023/05/29 (Mon) 16:07",
    "2023/05/29 (Mon) 16:30",
    "2023/05/29 (Mon) 19:36",
    "2023/05/30 (Tue) 05:10",
    "2023/05/30 (Tue) 13:34"
  ]
}