{
  "question_id": "603deb26",
  "question_type": "knowledge-update",
  "question_date": "2023/12/05 (Tue) 02:37",
  "num_sessions": 48,
  "num_turns": 472,
  "answer_session_ids": [
    "answer_8afdebac_1",
    "answer_8afdebac_2"
  ],
  "session_ids": [
    "37f66729",
    "answer_8afdebac_1",
    "sharegpt_DjfaDml_11",
    "433ce12c",
    "58e5adf2",
    "a55a5afc_2",
    "ede65c84_2",
    "sharegpt_43OIeUI_0",
    "feb5f98a_2",
    "5e867c2f_2",
    "28d52bff",
    "ultrachat_104321",
    "f0e71553_4",
    "sharegpt_w7bjHzU_78",
    "4f5880c6_2",
    "7badf4f3_3",
    "f379d356_3",
    "ultrachat_201507",
    "7db28e68_1",
    "sharegpt_Wj3iOcG_0",
    "ultrachat_69476",
    "ultrachat_409438",
    "5e523d80_3",
    "ultrachat_182173",
    "ultrachat_408354",
    "sharegpt_Ab5RUMY_0",
    "81f6b12f_2",
    "sharegpt_ZmDJxcL_0",
    "c4661b3c_1",
    "sharegpt_EtyzQD9_0",
    "sharegpt_dXzPvS4_0",
    "d05d6391_3",
    "f26846e1_3",
    "sharegpt_QDfpZQ4_0",
    "c77250d2",
    "ultrachat_98824",
    "ultrachat_324293",
    "sharegpt_mMTudFY_0",
    "9594de66_2",
    "ultrachat_453841",
    "sharegpt_etklNfN_11",
    "93191d30_2",
    "sharegpt_z6pSZ19_0",
    "7b0dea50_1",
    "88611fff",
    "ultrachat_191335",
    "answer_8afdebac_2",
    "ultrachat_528423"
  ],
  "dates": [
    "2023/08/04 (Fri) 04:05",
    "2023/08/11 (Fri) 17:11",
    "2023/08/11 (Fri) 00:49",
    "2023/08/11 (Fri) 19:46",
    "2023/08/12 (Sat) 03:22",
    "2023/08/14 (Mon) 21:57",
    "2023/08/14 (Mon) 16:17",
    "2023/08/15 (Tue) 08:11",
    "2023/08/16 (Wed) 06:11",
    "2023/08/27 (Sun) 17:04",
    "2023/08/28 (Mon) 02:17",
    "2023/08/28 (Mon) 21:23",
    "2023/08/30 (Wed) 18:47",
    "2023/08/31 (Thu) 04:27",
    "2023/09/01 (Fri) 19:58",
    "2023/09/01 (Fri) 09:03",
    "2023/09/06 (Wed) 02:04",
    "2023/09/08 (Fri) 23:53",
    "2023/09/12 (Tue) 13:39",
    "2023/09/23 (Sat) 19:16",
    "2023/09/23 (Sat) 08:05",
    "2023/09/24 (Sun) 21:36",
    "2023/09/26 (Tue) 22:22",
    "2023/09/28 (Thu) 07:18",
    "2023/10/01 (Sun) 22:47",
    "2023/10/02 (Mon) 00:53",
    "2023/10/03 (Tue) 07:29",
    "2023/10/04 (Wed) 13:26",
    "2023/10/08 (Sun) 16:28",
    "2023/10/12 (Thu) 20:53",
    "2023/10/21 (Sat) 21:49",
    "2023/10/22 (Sun) 11:56",
    "2023/10/28 (Sat) 19:09",
    "2023/10/31 (Tue) 04:52",
    "2023/11/07 (Tue) 17:29",
    "2023/11/11 (Sat) 06:32",
    "2023/11/13 (Mon) 04:54",
    "2023/11/16 (Thu) 00:25",
    "2023/11/22 (Wed) 12:18",
    "2023/11/23 (Thu) 01:58",
    "2023/11/23 (Thu) 23:49",
    "2023/11/25 (Sat) 14:27",
    "2023/11/25 (Sat) 21:20",
    "2023/11/29 (Wed) 21:01",
    "2023/11/30 (Thu) 16:07",
    "2023/11/30 (Thu) 15:10",
    "2023/11/30 (Thu) 01:59",
    "2023/12/01 (Fri) 00:05"
  ]
}